cenreg/__init__.py
cenreg/utils.py
cenreg/distribution/__init__.py
cenreg/distribution/empirical.py
cenreg/distribution/linear.py
cenreg/metric/__init__.py
cenreg/metric/cdf.py
cenreg/metric/cjd.py
cenreg/metric/quantile.py
cenreg/model/F2cjd_np.py
cenreg/model/__init__.py
cenreg/model/cjd2F_np.py
cenreg/model/copula_graphic.py
cenreg/model/copula_np.py
cenreg/model/kaplan_meier.py
cenreg/model/nonparametric.py
cenreg/pytorch/__init__.py
cenreg/pytorch/cjd2F.py
cenreg/pytorch/copula_torch.py
cenreg/pytorch/datamodule.py
cenreg/pytorch/distribution.py
cenreg/pytorch/loss_cdf.py
cenreg/pytorch/loss_cjd.py
cenreg/pytorch/loss_cont.py
cenreg/pytorch/mlp.py
cenreg/pytorch/utils.py
cenreg-0.0.6.dist-info/METADATA
cenreg-0.0.6.dist-info/WHEEL
cenreg-0.0.6.dist-info/licenses/LICENSE
cenreg-0.0.6.dist-info/RECORD
