Metadata-Version: 2.4
Name: cenreg
Version: 0.0.6
Summary: A Python library for censored regression.
Project-URL: Homepage, https://github.com/CyberAgentAILab/cenreg
Project-URL: Issues, https://github.com/CyberAgentAILab/cenreg/issues
Author-email: Hiroki Yanagisawa <yanagisawa_hiroki@cyberagent.co.jp>
License: Apache License (2.0)
License-File: LICENSE
Classifier: Operating System :: OS Independent
Classifier: Programming Language :: Python :: 3
Requires-Python: >=3.10
